pypcl/CMakeLists.txt
pypcl/__init__.py
pypcl/_pypcl.pyx
pypcl/pcd_reader.cpp
pypcl/pcd_reader.h
pypcl/pcd_reader.pxd
pypcl/_pypcl.cpython-311-aarch64-linux-gnu.so
pcl_python-0.0.4.dist-info/LICENSE
pcl_python-0.0.4.dist-info/METADATA
pcl_python-0.0.4.dist-info/WHEEL
pcl_python-0.0.4.dist-info/RECORD
